mkdocs_callouts/__init__.py
mkdocs_callouts/plugin.py
mkdocs_callouts/utils.py
mkdocs_callouts-1.14.1.dist-info/LICENSE
mkdocs_callouts-1.14.1.dist-info/METADATA
mkdocs_callouts-1.14.1.dist-info/WHEEL
mkdocs_callouts-1.14.1.dist-info/entry_points.txt
mkdocs_callouts-1.14.1.dist-info/top_level.txt
mkdocs_callouts-1.14.1.dist-info/RECORD
