Metadata-Version: 2.1
Name: mkdocs-callouts
Version: 1.14.1
Summary: A simple plugin that converts Obsidian style callouts and converts them into mkdocs supported 'admonitions' (a.k.a. callouts).
Author-email: Sondre Grønås <mail@sondregronas.com>
License: MIT
Project-URL: homepage, https://github.com/sondregronas/mkdocs-callouts
Project-URL: documentation, https://github.com/sondregronas/mkdocs-callouts
Project-URL: repository, https://github.com/sondregronas/mkdocs-callouts
Project-URL: issues, https://github.com/sondregronas/mkdocs-callouts/issues
Project-URL: funding, https://github.com/sponsors/sondregronas
Keywords: mkdocs,mkdocs-plugin,markdown,callouts,admonitions,obsidian
Classifier: Development Status :: 5 - Production/Stable
Classifier: License :: OSI Approved :: MIT License
Classifier: Programming Language :: Python
Classifier: Programming Language :: Python :: 3
Classifier: Programming Language :: Python :: 3 :: Only
Classifier: Topic :: Documentation
Classifier: Topic :: Software Development :: Documentation
Requires-Python: >=3.8
License-File: LICENSE
Requires-Dist: mkdocs >=1
Provides-Extra: tests
Requires-Dist: pytest ; extra == 'tests'
